sinaspider/__init__.py
sinaspider/helper.py
sinaspider/model.py
sinaspider/page.py
sinaspider/parser.py
sinaspider/script.py
sinaspider-0.4.1.dist-info/entry_points.txt
sinaspider-0.4.1.dist-info/LICENSE
sinaspider-0.4.1.dist-info/WHEEL
sinaspider-0.4.1.dist-info/METADATA
sinaspider-0.4.1.dist-info/RECORD
