Metadata-Version: 2.1
Name: sinaspider
Version: 0.4.1
Summary: Scraping Weibos
Author-email: BaoHengtao <baohengtao@users.noreply.github.com>
Requires-Python: ~=3.10
Classifier: License :: OSI Approved :: MIT License
Requires-Dist: requests
Requires-Dist: pendulum
Requires-Dist: rich
Requires-Dist: python-baseconv
Requires-Dist: PyExifTool
Requires-Dist: lxml
Requires-Dist: keyring
Requires-Dist: furl
Requires-Dist: requests-cache
Requires-Dist: typer
Requires-Dist: bs4
Requires-Dist: psycopg2
Requires-Dist: peewee
Requires-Dist: jupyterlab ; extra == "dev"
Requires-Dist: JLDracula ; extra == "dev"
Requires-Dist: jupyterlab_vim ; extra == "dev"
Requires-Dist: ptpython ; extra == "dev"
Requires-Dist: jupyterlab-lsp ; extra == "dev"
Requires-Dist: python-lsp-server ; extra == "dev"
Requires-Dist: pytest ; extra == "test"
Requires-Dist: pytest-pgsql ; extra == "test"
Project-URL: Home, https://github.com/baohengtao/sinaspider
Provides-Extra: dev
Provides-Extra: test
